actions/config.py
actions/declare_dark.py
actions/declare_missing.py
actions/remove_empty_dirs.py
cms_consistency/__init__.py
cms_consistency/version.py
cms_consistency/site_ctl/__init__.py
cms_consistency/site_ctl/site_ctl.py
site_ce/lfn_to_path.py
site_ce/merge_config.py
site_ce/path_list.py
cms_consistency-2.6.0.dist-info/LICENSE
cms_consistency-2.6.0.dist-info/METADATA
cms_consistency-2.6.0.dist-info/WHEEL
cms_consistency-2.6.0.dist-info/entry_points.txt
cms_consistency-2.6.0.dist-info/top_level.txt
cms_consistency-2.6.0.dist-info/RECORD
