Metadata-Version: 2.1
Name: cms-consistency
Version: 2.6.0
Summary: ('Rucio consistency enforcement for CMS',)
Home-page: https://github.com/rucio/cms_enforcement
Author: Igor Mandrichenko
Author-email: ivm@fnal.gov
License: BSD 3-clause
License-File: LICENSE
